twisted/plugins/magic_wormhole_mailbox.py
wormhole_mailbox_server/__init__.py
wormhole_mailbox_server/_version.py
wormhole_mailbox_server/database.py
wormhole_mailbox_server/increase_rlimits.py
wormhole_mailbox_server/server.py
wormhole_mailbox_server/server_tap.py
wormhole_mailbox_server/server_websocket.py
wormhole_mailbox_server/util.py
wormhole_mailbox_server/web.py
wormhole_mailbox_server/db-schemas/channel-v1.sql
wormhole_mailbox_server/db-schemas/channel-v2.sql
wormhole_mailbox_server/db-schemas/upgrade-channel-to-v2.sql
wormhole_mailbox_server/db-schemas/upgrade-usage-to-v2.sql
wormhole_mailbox_server/db-schemas/usage-v1.sql
wormhole_mailbox_server/db-schemas/usage-v2.sql
wormhole_mailbox_server/test/__init__.py
wormhole_mailbox_server/test/common.py
wormhole_mailbox_server/test/test_config.py
wormhole_mailbox_server/test/test_database.py
wormhole_mailbox_server/test/test_rlimits.py
wormhole_mailbox_server/test/test_server.py
wormhole_mailbox_server/test/test_service.py
wormhole_mailbox_server/test/test_stats.py
wormhole_mailbox_server/test/test_util.py
wormhole_mailbox_server/test/test_web.py
wormhole_mailbox_server/test/test_ws_client.py
wormhole_mailbox_server/test/ws_client.py
magic_wormhole_mailbox_server-0.5.1.dist-info/LICENSE
magic_wormhole_mailbox_server-0.5.1.dist-info/METADATA
magic_wormhole_mailbox_server-0.5.1.dist-info/WHEEL
magic_wormhole_mailbox_server-0.5.1.dist-info/top_level.txt
magic_wormhole_mailbox_server-0.5.1.dist-info/RECORD
