Metadata-Version: 2.1
Name: magic-wormhole-mailbox-server
Version: 0.5.1
Summary: Securely transfer data between computers
Home-page: https://github.com/warner/magic-wormhole-mailbox-server
Author: Brian Warner
Author-email: warner-magic-wormhole@lothar.com
License: MIT
Classifier: Development Status :: 4 - Beta
Classifier: Environment :: Console
Classifier: License :: OSI Approved :: MIT License
Classifier: Topic :: Security :: Cryptography
Classifier: Topic :: System :: Networking
Classifier: Topic :: System :: Systems Administration
Classifier: Topic :: Utilities
License-File: LICENSE
Requires-Dist: attrs>=16.3.0
Requires-Dist: twisted[tls]>=17.5.0
Requires-Dist: autobahn[twisted]>=0.14.1
Requires-Dist: setuptools
Requires-Dist: pywin32; sys_platform == "win32"
Provides-Extra: dev
Requires-Dist: mock; extra == "dev"
Requires-Dist: treq; extra == "dev"
Requires-Dist: tox; extra == "dev"
Requires-Dist: pyflakes; extra == "dev"
Provides-Extra: release
Requires-Dist: dulwich; extra == "release"
Requires-Dist: docutils; extra == "release"
Requires-Dist: gpg; extra == "release"
Requires-Dist: wheel; extra == "release"
